<?xml version="1.0" encoding="utf-8"?>
<object name="ARIANE 40+ R/B Satellite details 1995-021B NORAD 23561" type="Satellite">
	<images><image>garbage.png</image>
<!--[%IMAGES%]-->
<!-- <image>file.jpg</image> -->
	</images>
	<information>

<!-- Plain text -->
	</information>
	<characteristics>
<characteristic name="NORAD ID">23561	</characteristic><characteristic name="Int'l Code">1995-021B</characteristic>
<characteristic name="Perigee">769.0 km</characteristic>
<characteristic name="Apogee">780.8 km</characteristic>
<characteristic name="Inclination">98.7 °</characteristic>
<characteristic name="Period">100.2 minutes</characteristic>
<characteristic name="Semi major axis">7145 km</characteristic>
<characteristic name="Launch date">April 21, 1995</characteristic>
<characteristic name="Source">France (FR)</characteristic>
<characteristic name="Note">This is a ROCKET BODY</characteristic>

<!-- <characteristic name="name">value</characteristic> -->
	</characteristics>
	<link title="This article uses material from AFSPC">http://www.afspc.af.mil/</link>
</object>
